[
{"ocorrencia": "500", "pergunta": "Cliente possui outra conta aberta em período menor de 12 meses na Caixa com depósito inicial de valor inexpressivo?", "valor":"50", "grupo":"B"},
{"ocorrencia": "500", "pergunta": "Houve alteração de endereço e contato recente no cadastro do cliente?", "valor":"50", "grupo":"B"},
{"ocorrencia": "500", "pergunta": "A conta aberta em nome do cliente tem movimentação?", "valor":"25", "grupo":"A"},
{"ocorrencia": "500", "pergunta": "Existe contratação de crédito para a conta já aberta pelo CPF?", "valor":"25", "grupo":"A"},
{"ocorrencia": "500", "pergunta": "Existe ocorrência de devolução de cheques para a conta já aberta pelo CPF?", "valor":"50", "grupo":"B"},
{"ocorrencia": "500", "pergunta": "Existe movimentação de conta aberta com mesmo CPF com movimentação freqüente de TEDs e TEVs com retiradas no mesmo dia?", "valor":"50", "grupo":"B"},
{"ocorrencia": "500", "pergunta": "Existe vinculação de benefício em conta já aberta pelo CPF?", "valor":"25", "grupo":"A"},
{"ocorrencia": "500", "pergunta": "Existe movimentação de valores acima do esperado para renda e atividade econômica da conta aberta para mesmo CPF?", "valor":"50", "grupo":"B"},
{"ocorrencia": "500", "pergunta": "Existe emissão de boletos para conta já aberta com o CPF não condizente com atividade econômica do cliente?", "valor":"75", "grupo":"C"},
{"ocorrencia": "500", "pergunta": "Existe ocorrência de encerramento para a conta de mesmo CPF no sistema SIMGF?", "valor":"75", "grupo":"C"},
{"ocorrencia": "500", "pergunta": "Cliente alega delegar movimentação de conta aberta com o CPF por terceiros?", "valor":"50", "grupo":"B"},
{"ocorrencia": "500", "pergunta": "Existe emissão de cartões para conta de mesmo CPF?", "valor":"25", "grupo":"A"},
{"ocorrencia": "501", "pergunta": "Há sinais de cola, arranhões ou cortes ao redor da foto?", "valor":"75", "grupo":"C"},
{"ocorrencia": "501", "pergunta": "Há erros de preenchimento ou rasuras?", "valor":"75", "grupo":"C"},
{"ocorrencia": "501", "pergunta": "Há impressão digital borrada?", "valor":"75", "grupo":"C"},
{"ocorrencia": "501", "pergunta": "A fisionomia do portador é divergente da foto na Carteira de Identidade/CNH?", "valor":"50", "grupo":"B"},
{"ocorrencia": "501", "pergunta": "Há substituição ou sobreposição de foto?", "valor":"75", "grupo":"C"},
{"ocorrencia": "501", "pergunta": "A foto e impressão digital respeitam o espaço destinado a elas no espelho?", "valor":"25", "grupo":"A"},
{"ocorrencia": "501", "pergunta": "A foto é recente e o documento parece antigo ou vice-versa?", "valor":"50", "grupo":"B"},
{"ocorrencia": "501", "pergunta": "A data de nascimento é compatível com a fisionomia do portador?", "valor":"50", "grupo":"B"},
{"ocorrencia": "501", "pergunta": "Documento utilizado com data de emissão superior a 20 anos e dificulta identificação?", "valor":"50", "grupo":"B"},
{"ocorrencia": "501", "pergunta": "A fisionomia do cliente não é compatível com a data de expedição do RG?", "valor":"75", "grupo":"C"},
{"ocorrencia": "501", "pergunta": "Cliente possui outra conta aberta em período menor de 12 meses na Caixa com depósito inicial inexpressivo?", "valor":"50", "grupo":"B"},
{"ocorrencia": "501", "pergunta": "Houve alteração de endereço e contato recente no cadastro do cliente?", "valor":"50", "grupo":"B"},
{"ocorrencia": "501", "pergunta": "Cliente possui outra conta aberta no mesmo CPF e os documentos de abertura não batem com os apresentados?", "valor":"75", "grupo":"C"},
{"ocorrencia": "501", "pergunta": "Existe ocorrência de encerramento para a conta de mesmo CPF no sistema SIMGF?", "valor":"50", "grupo":"B"},
{"ocorrencia": "501", "pergunta": "Fotografia do documento apresentado diverge do sistema de BIOMETRIA?", "valor":"75", "grupo":"C"},
{"ocorrencia": "501", "pergunta": "Dados do cliente divergem dos encontrados no site do TSE?", "valor":"75", "grupo":"C"},
{"ocorrencia": "501", "pergunta": "Cliente alega ter tido documento roubados ou perdidos e não foi feito Boletim de Ocorrência?", "valor":"50", "grupo":"B"},
{"ocorrencia": "501", "pergunta": "Existem documentos semelhantes em ocorrência de fraude documental no SICOD?", "valor":"75", "grupo":"C"},
{"ocorrencia": "501", "pergunta": "Existe emissão de cartões para a conta de mesmo CPF do cliente?", "valor":"25", "grupo":"A"},
{"ocorrencia": "501", "pergunta": "Existe contratação de crédito para a conta já aberta pelo CPF?", "valor":"25", "grupo":"A"},
{"ocorrencia": "501", "pergunta": "O local de abertura da conta de mesmo CPF discrepante do comprovante de renda apresentado na proposta ou na localização do vinculo empregatício?", "valor":"50", "grupo":"B"},
{"ocorrencia": "502", "pergunta": "Cliente alega ter tido documento roubados ou perdidos e não foi feito Boletim de Ocorrência?", "valor":"50", "grupo":"B"},
{"ocorrencia": "502", "pergunta": "Há sinais de cola, arranhões ou cortes ao redor da foto?", "valor":"75", "grupo":"C"},
{"ocorrencia": "502", "pergunta": "Há erros de preenchimento ou rasuras?", "valor":"75", "grupo":"C"},
{"ocorrencia": "502", "pergunta": "Há impressão digital borrada?", "valor":"75", "grupo":"C"},
{"ocorrencia": "502", "pergunta": "A fisionomia do portador é divergente da foto na Carteira de Identidade/CNH?", "valor":"75", "grupo":"C"},
{"ocorrencia": "502", "pergunta": "Há substituição ou sobreposição de foto?", "valor":"75", "grupo":"C"},
{"ocorrencia": "502", "pergunta": "A foto e impressão digital respeitam o espaço destinado a elas no espelho?", "valor":"50", "grupo":"B"},
{"ocorrencia": "502", "pergunta": "A foto é recente e o documento parece antigo ou vice-versa?", "valor":"50", "grupo":"B"},
{"ocorrencia": "502", "pergunta": "A data de nascimento é compatível com a fisionomia do portador?", "valor":"50", "grupo":"B"},
{"ocorrencia": "502", "pergunta": "A fisionomia do cliente não é compatível com a data de expedição do RG?", "valor":"50", "grupo":"B"},
{"ocorrencia": "502", "pergunta": "Cliente possui outra conta aberta em período menor de 12 meses na Caixa com depósito inicial inexpressivo?", "valor":"50", "grupo":"B"},
{"ocorrencia": "502", "pergunta": "Houve alteração de endereço e contato recente no cadastro do cliente?", "valor":"50", "grupo":"B"},
{"ocorrencia": "502", "pergunta": "Cliente possui outra conta aberta no mesmo CPF e os documentos de abertura não batem com os apresentados?", "valor":"75", "grupo":"C"},
{"ocorrencia": "502", "pergunta": "Existe ocorrência de encerramento para a conta de mesmo CPF no sistema SIMGF?", "valor":"50", "grupo":"B"},
{"ocorrencia": "502", "pergunta": "Fotografia do documento apresentado diverge do sistema de BIOMETRIA?", "valor":"75", "grupo":"C"},
{"ocorrencia": "502", "pergunta": "Existem documentos semelhantes em ocorrência de fraude documental no SICOD?", "valor":"75", "grupo":"C"},
{"ocorrencia": "502", "pergunta": "Existe emissão de cartões para a conta de mesmo CPF do cliente?", "valor":"25", "grupo":"A"},
{"ocorrencia": "502", "pergunta": "Existe contratação de crédito para a conta já aberta pelo CPF?", "valor":"25", "grupo":"A"},
{"ocorrencia": "507", "pergunta": "Houve alteração de endereço e contato recente no cadastro do cliente?", "valor":"50", "grupo":"B"},
{"ocorrencia": "507", "pergunta": "Existe contratação de crédito para a conta já aberta pelo CPF?", "valor":"25", "grupo":"A"},
{"ocorrencia": "507", "pergunta": "Existe vinculação de benefício em conta já aberta pelo CPF?", "valor":"25", "grupo":"A"},
{"ocorrencia": "507", "pergunta": "Cliente alega delegar movimentação de conta aberta com o CPF por terceiros?", "valor":"50", "grupo":"B"},
{"ocorrencia": "507", "pergunta": "Existe emissão de cartões para conta de mesmo CPF?", "valor":"25", "grupo":"A"},
{"ocorrencia": "507", "pergunta": "Existe emissão de cartão cidadão para o cliente?", "valor":"25", "grupo":"A"},
{"ocorrencia": "507", "pergunta": "Dados do cliente divergem dos encontrados no site do TSE?", "valor":"75", "grupo":"C"}
]